poisson_2d/__init__.py
poisson_2d/solver.py
poisson_2d-0.1.0.dist-info/METADATA
poisson_2d-0.1.0.dist-info/WHEEL
poisson_2d-0.1.0.dist-info/RECORD
