Metadata-Version: 2.1
Name: poisson-2d
Version: 0.1.0
Summary: 
Author: Your Name
Author-email: you@example.com
Requires-Python: >=3.12,<4.0
Classifier: Programming Language :: Python :: 3
Classifier: Programming Language :: Python :: 3.12
Requires-Dist: matplotlib (>=3.9.2,<4.0.0)
Requires-Dist: scipy (>=1.14.0,<2.0.0)
Requires-Dist: sympy (>=1.13.2,<2.0.0)
